kerasmodels/__init__.py
kerasmodels/engine.py
kerasmodels/mnasnet.py
kerasmodels/mobilenetv2.py
kerasmodels/shufflenetv2.py
kerasmodels/squeezenet.py
kerasmodels-0.1.3.dist-info/LICENSE
kerasmodels-0.1.3.dist-info/METADATA
kerasmodels-0.1.3.dist-info/WHEEL
kerasmodels-0.1.3.dist-info/top_level.txt
kerasmodels-0.1.3.dist-info/RECORD
