Metadata-Version: 2.1
Name: kerasmodels
Version: 0.1.3
Summary: keras pretrained models
Home-page: https://github.com/kevin970401/keras-pretrainedmodels
Author: kevin970401
Author-email: kevin970401@gmail.com
License: MIT
Keywords: kerasmodels
Platform: UNKNOWN
Requires-Python: >=3.6
